dstructure/Algos.py
dstructure/Sorting.py
dstructure/__init__.py
dstructure/binarytree.py
dstructure/exceptions.py
dstructure/linkedlist.py
dstructure/queues.py
dstructure/stack.py
Gsauce_pyds-1.0.0.dist-info/METADATA
Gsauce_pyds-1.0.0.dist-info/WHEEL
Gsauce_pyds-1.0.0.dist-info/top_level.txt
Gsauce_pyds-1.0.0.dist-info/RECORD
