Metadata-Version: 2.1
Name: Gsauce-pyds
Version: 1.0.0
Summary: Some useful and known data structure.
Home-page: https://github.com/GSAUC3/Gsauce-pyds
Author: Rajarshi Banerjee
Author-email: sambaner1050@outlook.com 
License: MIT
Keywords: python,linked list,singly linked list,Binary Search Tree,Binary Tree
Classifier: Operating System :: OS Independent
Classifier: Programming Language :: Python :: 3
Classifier: Programming Language :: Python :: 2
Classifier: License :: OSI Approved :: MIT License
